{
    "Game Behavior": {
        "checkpoints": [
            {
                "steps": 0,
                "file_path": "results/12/Game Behavior/Game Behavior-0.onnx",
                "reward": null,
                "creation_time": 1606591631.904018
            }
        ],
        "final_checkpoint": {
            "steps": 0,
            "file_path": "results/12/Game Behavior.onnx",
            "reward": null,
            "creation_time": 1606591631.904018
        }
    },
    "metadata": {
        "stats_format_version": "0.2.0",
        "mlagents_version": "0.22.0",
        "torch_version": "1.7.0",
        "tensorflow_version": "2.3.1"
    }
}